multinut/__init__.py
multinut/env.py
multinut-0.2.2.dist-info/METADATA
multinut-0.2.2.dist-info/WHEEL
multinut-0.2.2.dist-info/top_level.txt
multinut-0.2.2.dist-info/RECORD
