Metadata-Version: 2.4
Name: multinut
Version: 0.2.2
Summary: A completely unnecessary multitool module.
Home-page: https://github.com/ChipperFluff/multinut
Author: Chipperfluff
Author-email: i96774080@gmail.com
Classifier: Programming Language :: Python :: 3
Requires-Python: >=3.6
Requires-Dist: dotenv
Dynamic: author
Dynamic: author-email
Dynamic: classifier
Dynamic: description
Dynamic: description-content-type
Dynamic: home-page
Dynamic: requires-dist
Dynamic: requires-python
Dynamic: summary
